batching_kafka_consumer/__init__.py
batching_kafka_consumer-0.0.5.dist-info/LICENSE
batching_kafka_consumer-0.0.5.dist-info/METADATA
batching_kafka_consumer-0.0.5.dist-info/WHEEL
batching_kafka_consumer-0.0.5.dist-info/top_level.txt
batching_kafka_consumer-0.0.5.dist-info/RECORD
