Metadata-Version: 2.1
Name: batching-kafka-consumer
Version: 0.0.5
Summary: Kafka Consumer abstraction that assists with processing batches and committing offsets.
Home-page: https://github.com/getsentry/batching-kafka-consumer
Author: Sentry Team and Contributors
Author-email: hello@getsentry.com
License: BSD
Platform: UNKNOWN
Classifier: Development Status :: 5 - Production/Stable
Classifier: Environment :: Web Environment
Classifier: Intended Audience :: Developers
Classifier: License :: OSI Approved :: BSD License
Classifier: Operating System :: OS Independent
Classifier: Programming Language :: Python
Classifier: Programming Language :: Python :: 2
Classifier: Programming Language :: Python :: 2.7
Classifier: Programming Language :: Python :: 3
Classifier: Programming Language :: Python :: 3.7
Classifier: Topic :: Software Development :: Libraries :: Python Modules
Requires-Dist: confluent-kafka (==0.11.5)
